{"ts":"2025-04-09T21:48:45.334Z","level":"error","error":{"originalError":{"name":"NotFound","message":"{\n  \"status\": 404,\n  \"statusText\": \"Not Found\",\n  \"message\": \"The resource could not be found.\",\n  \"details\": {\n    \"type\": \"Space\",\n    \"id\": \"%22%22\"\n  },\n  \"request\": {\n    \"url\": \"/spaces/\\\"\\\"\",\n    \"headers\": {\n      \"Accept\": \"application/json, text/plain, */*\",\n      \"Content-Type\": \"application/vnd.contentful.management.v1+json\",\n      \"X-Contentful-User-Agent\": \"app contentful.export/7.19.158; feature library-export; sdk contentful-management.js/11.35.1; platform node.js/v23.11.0; os macOS/v23.11.0;\",\n      \"CF-Sequence\": \"e45ebc4f-8284-4b90-8012-c4684211d7d4\",\n      \"Authorization\": \"Bearer ...er \\\"\\\"\",\n      \"User-Agent\": \"axios/1.7.7\",\n      \"Accept-Encoding\": \"gzip, compress, deflate, br\"\n    },\n    \"method\": \"get\"\n  },\n  \"requestId\": \"e073f0f0-6900-4c07-945d-7e90be5ac0f7\"\n}"},"data":{"status":404,"statusText":"Not Found","message":"The resource could not be found.","details":{"type":"Space","id":"%22%22"},"request":{"url":"/spaces/\"\"","headers":{"Accept":"application/json, text/plain, */*","Content-Type":"application/vnd.contentful.management.v1+json","X-Contentful-User-Agent":"app contentful.export/7.19.158; feature library-export; sdk contentful-management.js/11.35.1; platform node.js/v23.11.0; os macOS/v23.11.0;","CF-Sequence":"e45ebc4f-8284-4b90-8012-c4684211d7d4","Authorization":"Bearer ...er \"\"","User-Agent":"axios/1.7.7","Accept-Encoding":"gzip, compress, deflate, br"},"method":"get"},"requestId":"e073f0f0-6900-4c07-945d-7e90be5ac0f7"}}}